solarmach/__init__.py
solarmach/_version.py
solarmach/pfss_utilities.py
solarmach/version.py
solarmach/tests/__init__.py
solarmach/tests/figure_hashes_mpl_391.json
solarmach/tests/test.py
solarmach/tests/baseline/test_solarmach_pfss.png
solarmach/tests/baseline/test_solarmach_plot_Carrington-numbers-True-270.png
solarmach/tests/baseline/test_solarmach_plot_Stonyhurst-letters-False-0.png
solarmach-0.5.2.dist-info/licenses/LICENSE.rst
solarmach-0.5.2.dist-info/METADATA
solarmach-0.5.2.dist-info/WHEEL
solarmach-0.5.2.dist-info/top_level.txt
solarmach-0.5.2.dist-info/RECORD
