Metadata-Version: 2.4
Name: solarmach
Version: 0.5.2
Summary: Multi-spacecraft longitudinal configuration plotter
Author-email: Jan Gieseler <jan.gieseler@utu.fi>
License-Expression: BSD-3-Clause
Project-URL: repository, https://github.com/jgieseler/solarmach
Classifier: Intended Audience :: Science/Research
Classifier: Natural Language :: English
Classifier: Operating System :: OS Independent
Classifier: Programming Language :: Python
Classifier: Programming Language :: Python :: 3.10
Classifier: Programming Language :: Python :: 3.11
Classifier: Programming Language :: Python :: 3.12
Classifier: Programming Language :: Python :: 3.13
Classifier: Topic :: Scientific/Engineering :: Physics
Requires-Python: >=3.10
License-File: LICENSE.rst
Requires-Dist: astropy
Requires-Dist: cmasher
Requires-Dist: drms
Requires-Dist: imageio>=2.31.6
Requires-Dist: Jinja2
Requires-Dist: lxml
Requires-Dist: matplotlib
Requires-Dist: numpy
Requires-Dist: orjson
Requires-Dist: pandas
Requires-Dist: plotly
Requires-Dist: python-dateutil
Requires-Dist: scipy
Requires-Dist: speasy>=1.2.7
Requires-Dist: sunkit_magex
Requires-Dist: sunpy
Requires-Dist: threadpoolctl
Requires-Dist: tqdm
Requires-Dist: zeep
Provides-Extra: test
Requires-Dist: pytest; extra == "test"
Requires-Dist: pytest-doctestplus; extra == "test"
Requires-Dist: pytest-cov; extra == "test"
Requires-Dist: pytest-mpl; extra == "test"
Provides-Extra: docs
Requires-Dist: sphinx; extra == "docs"
Requires-Dist: sphinx-automodapi; extra == "docs"
Requires-Dist: numpydoc; extra == "docs"
Requires-Dist: sphinx_rtd_theme; extra == "docs"
Dynamic: license-file
